[
  {
    "Name": "ts_wall_03",
    "Format": "CMPR",
    "AlphaSetting": 0,
    "WrapS": "Repeat",
    "WrapT": "Repeat",
    "PaletteFormat": "IA8",
    "MipMap": 0,
    "EdgeLOD": false,
    "BiasClamp": false,
    "MaxAniso": 0,
    "MinFilter": "Linear",
    "MagFilter": "Linear",
    "MinLOD": 0.0,
    "MaxLOD": 0.0,
    "LodBias": 0.0
  },
  {
    "Name": "HighLightSample",
    "Format": "I8",
    "AlphaSetting": 0,
    "WrapS": "Repeat",
    "WrapT": "Repeat",
    "PaletteFormat": "IA8",
    "MipMap": 0,
    "EdgeLOD": false,
    "BiasClamp": false,
    "MaxAniso": 0,
    "MinFilter": "Linear",
    "MagFilter": "Linear",
    "MinLOD": 0.0,
    "MaxLOD": 0.0,
    "LodBias": 0.0
  },
  {
    "Name": "ts_wall_01",
    "Format": "CMPR",
    "AlphaSetting": 0,
    "WrapS": "Repeat",
    "WrapT": "Repeat",
    "PaletteFormat": "IA8",
    "MipMap": 0,
    "EdgeLOD": false,
    "BiasClamp": false,
    "MaxAniso": 0,
    "MinFilter": "Linear",
    "MagFilter": "Linear",
    "MinLOD": 0.0,
    "MaxLOD": 0.0,
    "LodBias": 0.0
  },
  {
    "Name": "ts_saku_01s",
    "Format": "IA4",
    "AlphaSetting": 0,
    "WrapS": "Repeat",
    "WrapT": "Repeat",
    "PaletteFormat": "IA8",
    "MipMap": 0,
    "EdgeLOD": false,
    "BiasClamp": false,
    "MaxAniso": 0,
    "MinFilter": "Linear",
    "MagFilter": "Linear",
    "MinLOD": 0.0,
    "MaxLOD": 3.0,
    "LodBias": 0.0
  },
  {
    "Name": "ts_wall_02",
    "Format": "CMPR",
    "AlphaSetting": 0,
    "WrapS": "Repeat",
    "WrapT": "Repeat",
    "PaletteFormat": "IA8",
    "MipMap": 0,
    "EdgeLOD": false,
    "BiasClamp": false,
    "MaxAniso": 0,
    "MinFilter": "Linear",
    "MagFilter": "Linear",
    "MinLOD": 0.0,
    "MaxLOD": 0.0,
    "LodBias": 0.0
  },
  {
    "Name": "ts_wall_04",
    "Format": "CMPR",
    "AlphaSetting": 0,
    "WrapS": "Repeat",
    "WrapT": "Repeat",
    "PaletteFormat": "IA8",
    "MipMap": 0,
    "EdgeLOD": false,
    "BiasClamp": false,
    "MaxAniso": 0,
    "MinFilter": "Linear",
    "MagFilter": "Linear",
    "MinLOD": 0.0,
    "MaxLOD": 0.0,
    "LodBias": 0.0
  },
  {
    "Name": "ts_saku_02",
    "Format": "CMPR",
    "AlphaSetting": 0,
    "WrapS": "Repeat",
    "WrapT": "Repeat",
    "PaletteFormat": "IA8",
    "MipMap": 1,
    "EdgeLOD": false,
    "BiasClamp": false,
    "MaxAniso": 0,
    "MinFilter": "LinearMipmapLinear",
    "MagFilter": "Linear",
    "MinLOD": 0.0,
    "MaxLOD": 4.0,
    "LodBias": -0.399999976
  },
  {
    "Name": "ts_saku_01",
    "Format": "CMPR",
    "AlphaSetting": 0,
    "WrapS": "Repeat",
    "WrapT": "Repeat",
    "PaletteFormat": "IA8",
    "MipMap": 0,
    "EdgeLOD": false,
    "BiasClamp": false,
    "MaxAniso": 0,
    "MinFilter": "Linear",
    "MagFilter": "Linear",
    "MinLOD": 0.0,
    "MaxLOD": 0.0,
    "LodBias": 0.0
  },
  {
    "Name": "ta_cornhead_01",
    "Format": "CMPR",
    "AlphaSetting": 0,
    "WrapS": "Repeat",
    "WrapT": "Repeat",
    "PaletteFormat": "IA8",
    "MipMap": 0,
    "EdgeLOD": false,
    "BiasClamp": false,
    "MaxAniso": 0,
    "MinFilter": "Linear",
    "MagFilter": "Linear",
    "MinLOD": 0.0,
    "MaxLOD": 0.0,
    "LodBias": 0.0
  },
  {
    "Name": "TrussFrame",
    "Format": "IA4",
    "AlphaSetting": 0,
    "WrapS": "Repeat",
    "WrapT": "Repeat",
    "PaletteFormat": "IA8",
    "MipMap": 0,
    "EdgeLOD": false,
    "BiasClamp": false,
    "MaxAniso": 0,
    "MinFilter": "Linear",
    "MagFilter": "Linear",
    "MinLOD": 0.0,
    "MaxLOD": 0.0,
    "LodBias": 0.0
  }
]